setup.py
bd_distributions/Binomialdistribution.py
bd_distributions/Gaussiandistribution.py
bd_distributions/Generaldistribution.py
bd_distributions/__init__.py
bd_distributions.egg-info/PKG-INFO
bd_distributions.egg-info/SOURCES.txt
bd_distributions.egg-info/dependency_links.txt
bd_distributions.egg-info/not-zip-safe
bd_distributions.egg-info/top_level.txt